yourapp/__init__.py
yourapp/__main__.py
yourapp/main.py
yourapp/py.typed
python_distribution_example-1.0.0.dist-info/LICENSE
python_distribution_example-1.0.0.dist-info/METADATA
python_distribution_example-1.0.0.dist-info/WHEEL
python_distribution_example-1.0.0.dist-info/entry_points.txt
python_distribution_example-1.0.0.dist-info/RECORD
