Metadata-Version: 2.1
Name: python-distribution-example
Version: 1.0.0
Summary: An example of Python application distribution.
License: Apache-2.0
Author: JP Hutchins
Author-email: jphutchins@gmail.com
Requires-Python: >=3.10,<3.13
Classifier: License :: OSI Approved :: Apache Software License
Classifier: Programming Language :: Python :: 3
Classifier: Programming Language :: Python :: 3.10
Classifier: Programming Language :: Python :: 3.11
Classifier: Programming Language :: Python :: 3.12
